dahu-2024.2.0.dist-info/METADATA
dahu-2024.2.0.dist-info/WHEEL
dahu-2024.2.0.dist-info/entry_points.txt
dahu-2024.2.0.dist-info/LICENSE
dahu/version.py
dahu/app/reprocess.py
dahu/app/tango_server.py
dahu/app/tango_register.py
dahu/test/__init__.py
dahu/test/utilstest.py
dahu/test/test_all.py
dahu/test/test_plugin.py
dahu/test/test_job.py
dahu/test/test_cache.py
dahu/cache.py
dahu/__init__.py
dahu/job.py
dahu/utils.py
dahu/factory.py
dahu/server.py
dahu/plugin.py
dahu/plugins/bm29/common.py
dahu/plugins/bm29/hplc.py
dahu/plugins/bm29/__init__.py
dahu/plugins/bm29/integrate.py
dahu/plugins/bm29/ispyb.py
dahu/plugins/bm29/nexus.py
dahu/plugins/bm29/subtracte.py
dahu/plugins/id02/single_detector.py
dahu/plugins/id02/__init__.py
dahu/plugins/id02/common.py
dahu/plugins/id02/metadata.py
dahu/plugins/id02/xpcs.py
dahu/plugins/id02/nexus.py
dahu/plugins/id31/__init__.py
dahu/plugins/id31/calculate_flux.py
dahu/plugins/example.py
dahu/plugins/focus.py
dahu/plugins/id15.py
dahu/plugins/id15v2.py
dahu/plugins/id27.py
dahu/plugins/pyfai.py
dahu-2024.2.0.dist-info/RECORD
