Metadata-Version: 2.1
Name: dahu
Version: 2024.2.0
Summary: "Python lightweight, plugin based, data analysis engine"
Home-page: http://www.silx.org
Author-Email: Jérôme Kieffer <jerome.kieffer@esrf.fr>
License:  Permission is hereby granted, free of charge, to any person obtaining a copy
Classifier: Development Status :: 3 - Alpha
Classifier: Environment :: Console
Classifier: Environment :: MacOS X
Classifier: Environment :: Win32 (MS Windows)
Classifier: Environment :: X11 Applications :: Qt
Classifier: Intended Audience :: Education
Classifier: Intended Audience :: Science/Research
Classifier: License :: OSI Approved :: MIT License
Classifier: License :: OSI Approved :: GNU Lesser General Public License v2 or later (LGPLv2+)
Classifier: Natural Language :: English
Classifier: Operating System :: MacOS
Classifier: Operating System :: Microsoft :: Windows
Classifier: Operating System :: POSIX
Classifier: Programming Language :: Cython
Classifier: Programming Language :: Python :: 3.6
Classifier: Programming Language :: Python :: 3.7
Classifier: Programming Language :: Python :: 3.8
Classifier: Programming Language :: Python :: Implementation :: CPython
Classifier: Topic :: Scientific/Engineering :: Physics
Classifier: Topic :: Software Development :: Libraries :: Python Modules
Project-URL: Homepage, http://www.silx.org
Project-URL: Documentation, http://www.silx.org/doc/dahu/latest/
Project-URL: Source, https://github.com/kif/dahu
Project-URL: Download, https://github.com/kif/dahu/releases
Project-URL: Tracker, https://github.com/kif/dahu/issues
Requires-Python: >=3.7
Requires-Dist: numpy>=1.10
